[1,["11bc3d423@6c48a"],["_textureSource"],["cc.SpriteFrame"],0,[[[{"name":"leave04","rect":{"x":3,"y":3,"width":181,"height":70},"offset":{"x":0,"y":0},"originalSize":{"width":181,"height":70},"rotated":false,"capInsets":[0,0,0,0],"packable":true,"pixelsToUnit":100,"pivot":{"x":0.5,"y":0.5},"meshType":0}],[0],0,[0],[0],[0]],[[{"name":"leave02","rect":{"x":190,"y":3,"width":181,"height":70},"offset":{"x":0,"y":0},"originalSize":{"width":181,"height":70},"rotated":false,"capInsets":[0,0,0,0],"packable":true,"pixelsToUnit":100,"pivot":{"x":0.5,"y":0.5},"meshType":0}],[0],0,[0],[0],[0]],[[{"name":"balanceImg01","rect":{"x":751,"y":3,"width":142,"height":42},"offset":{"x":0,"y":0},"originalSize":{"width":142,"height":42},"rotated":false,"capInsets":[0,0,0,0],"packable":true,"pixelsToUnit":100,"pivot":{"x":0.5,"y":0.5},"meshType":0}],[0],0,[0],[0],[0]],[[{"name":"leave01","rect":{"x":377,"y":3,"width":181,"height":70},"offset":{"x":0,"y":0},"originalSize":{"width":181,"height":70},"rotated":false,"capInsets":[0,0,0,0],"packable":true,"pixelsToUnit":100,"pivot":{"x":0.5,"y":0.5},"meshType":0}],[0],0,[0],[0],[0]],[[{"name":"balanceCoin01","rect":{"x":899,"y":3,"width":46,"height":44},"offset":{"x":0,"y":0},"originalSize":{"width":46,"height":44},"rotated":false,"capInsets":[0,0,0,0],"packable":true,"pixelsToUnit":100,"pivot":{"x":0.5,"y":0.5},"meshType":0}],[0],0,[0],[0],[0]]]]
